django_link_shortener-1.1.0.dist-info/licenses/LICENSE
shortener/__init__.py
shortener/admin.py
shortener/apps.py
shortener/models.py
shortener/shortener.py
shortener/urls.py
shortener/views.py
shortener/migrations/0001_initial.py
shortener/migrations/0002_auto_20190528_1522.py
shortener/migrations/0003_auto_20190528_1558.py
shortener/migrations/0004_alter_urlprofile_enabled.py
shortener/migrations/0005_alter_urlmap_id_alter_urlprofile_id.py
shortener/migrations/__init__.py
django_link_shortener-1.1.0.dist-info/METADATA
django_link_shortener-1.1.0.dist-info/WHEEL
django_link_shortener-1.1.0.dist-info/top_level.txt
django_link_shortener-1.1.0.dist-info/RECORD
